anchor_pki/__init__.py
anchor_pki/acme.py
anchor_pki/anchor.py
anchor_pki/autocert/__init__.py
anchor_pki/autocert/configuration.py
anchor_pki/autocert/identifier_policy.py
anchor_pki/autocert/managed_certificate.py
anchor_pki/autocert/manager.py
anchor_pki/autocert/policy_check.py
anchor_pki/autocert/sni_callback.py
anchor_pki/autocert/terms_of_service.py
anchor_pki-0.3.0.dist-info/LICENSE
anchor_pki-0.3.0.dist-info/METADATA
anchor_pki-0.3.0.dist-info/WHEEL
anchor_pki-0.3.0.dist-info/RECORD
