Metadata-Version: 2.1
Name: anchor-pki
Version: 0.3.0
Summary: Client library for Anchor PKI. See https://anchor.dev/ for details'
Home-page: https://anchor.dev
License: MIT
Keywords: anchor,pki,acme
Author: Anchor
Author-email: support@anchor.dev
Requires-Python: >=3.9,<4.0
Classifier: Development Status :: 4 - Beta
Classifier: Intended Audience :: Developers
Classifier: License :: OSI Approved :: MIT License
Classifier: Programming Language :: Python :: 3
Classifier: Programming Language :: Python :: 3.9
Classifier: Programming Language :: Python :: 3.10
Classifier: Programming Language :: Python :: 3.11
Classifier: Programming Language :: Python :: 3.12
Classifier: Topic :: Security
Classifier: Topic :: System :: Networking
Requires-Dist: acme (>=2.6.0,<3.0.0)
Requires-Dist: diskcache (>=5.6.3,<6.0.0)
